pokemon_formats/PokePaste.py
pokemon_formats/Showdown.py
pokemon_formats/__init__.py
pokemon_formats-1.0.2.dist-info/METADATA
pokemon_formats-1.0.2.dist-info/WHEEL
pokemon_formats-1.0.2.dist-info/licenses/LICENSE
pokemon_formats-1.0.2.dist-info/RECORD
