Metadata-Version: 2.1
Name: pokemon_formats
Version: 1.0.2
Summary: A package for decoding and encoding pokemon showdown sets as well as uploading and retrieving teams from PokePaste.
Project-URL: Homepage, https://github.com/eyalmen/pokemon_formats
Project-URL: Bug Tracker, https://github.com/eyalmen/pokemon_formats/issues
Author-email: David Eyal <dave.eyal@gmail.com>
License-File: LICENSE
Classifier: License :: OSI Approved :: MIT License
Classifier: Operating System :: OS Independent
Classifier: Programming Language :: Python :: 3
Requires-Python: >=3.7
